triggon/__init__.py
triggon/py.typed
triggon/trig_func.py
triggon/triggon.py
triggon/triggon.pyi
triggon/_internal/_debug.py
triggon/_internal/_err_handler.py
triggon/_internal/_exceptions.py
triggon/_internal/_frame_utils.py
triggon/_internal/_methods.py
triggon/_internal/_revert.py
triggon/_internal/_sentinel.py
triggon/_internal/_set_trigger.py
triggon/_internal/_switch_var.py
triggon/_internal/_var_analysis.py
triggon/_internal/_var_update.py
triggon-1.0.1.dist-info/licenses/LICENSE
triggon-1.0.1.dist-info/METADATA
triggon-1.0.1.dist-info/WHEEL
triggon-1.0.1.dist-info/top_level.txt
triggon-1.0.1.dist-info/RECORD
