Metadata-Version: 2.4
Name: triggon
Version: 1.0.1
Summary: Dynamically switches values and functions at labeled trigger points, with support for early returns and function calls.
Author-email: Tsuruko <tsuruko-12@outlook.com>
Maintainer-email: Tsuruko <tsuruko-12@outlook.com>
License: MIT License
Project-URL: Homepage, https://github.com/tsuruko12/triggon
Project-URL: Source, https://github.com/tsuruko12/triggon
Project-URL: Bug Tracker, https://github.com/tsuruko12/triggon/issues
Project-URL: Changelog, https://github.com/tsuruko12/triggon/blob/main/CHANGELOG.md
Keywords: python,python-Libraries,triggon,automation,dynamic-switching,delayed-execution,early-return,lightweight
Classifier: Programming Language :: Python :: 3.12
Classifier: Programming Language :: Python :: 3.13
Classifier: Development Status :: 4 - Beta
Classifier: License :: OSI Approved :: MIT License
Classifier: Intended Audience :: Developers
Classifier: Topic :: Software Development :: Libraries :: Python Modules
Requires-Python: >=3.13
License-File: LICENSE
Dynamic: license-file
